good_day.py
good_day-0.2.1.dist-info/LICENSE
good_day-0.2.1.dist-info/METADATA
good_day-0.2.1.dist-info/WHEEL
good_day-0.2.1.dist-info/entry_points.txt
good_day-0.2.1.dist-info/top_level.txt
good_day-0.2.1.dist-info/RECORD
